odoo/addons/stock_picking_backorder_strategy/README.rst
odoo/addons/stock_picking_backorder_strategy/__init__.py
odoo/addons/stock_picking_backorder_strategy/__manifest__.py
odoo/addons/stock_picking_backorder_strategy/i18n/am.po
odoo/addons/stock_picking_backorder_strategy/i18n/bg.po
odoo/addons/stock_picking_backorder_strategy/i18n/bs.po
odoo/addons/stock_picking_backorder_strategy/i18n/ca.po
odoo/addons/stock_picking_backorder_strategy/i18n/ca_ES.po
odoo/addons/stock_picking_backorder_strategy/i18n/cs.po
odoo/addons/stock_picking_backorder_strategy/i18n/de.po
odoo/addons/stock_picking_backorder_strategy/i18n/el_GR.po
odoo/addons/stock_picking_backorder_strategy/i18n/en_AU.po
odoo/addons/stock_picking_backorder_strategy/i18n/en_GB.po
odoo/addons/stock_picking_backorder_strategy/i18n/es.po
odoo/addons/stock_picking_backorder_strategy/i18n/es_AR.po
odoo/addons/stock_picking_backorder_strategy/i18n/es_CL.po
odoo/addons/stock_picking_backorder_strategy/i18n/es_CO.po
odoo/addons/stock_picking_backorder_strategy/i18n/es_CR.po
odoo/addons/stock_picking_backorder_strategy/i18n/es_DO.po
odoo/addons/stock_picking_backorder_strategy/i18n/es_EC.po
odoo/addons/stock_picking_backorder_strategy/i18n/es_MX.po
odoo/addons/stock_picking_backorder_strategy/i18n/es_VE.po
odoo/addons/stock_picking_backorder_strategy/i18n/et.po
odoo/addons/stock_picking_backorder_strategy/i18n/eu.po
odoo/addons/stock_picking_backorder_strategy/i18n/fa.po
odoo/addons/stock_picking_backorder_strategy/i18n/fi.po
odoo/addons/stock_picking_backorder_strategy/i18n/fr.po
odoo/addons/stock_picking_backorder_strategy/i18n/fr_CH.po
odoo/addons/stock_picking_backorder_strategy/i18n/fr_FR.po
odoo/addons/stock_picking_backorder_strategy/i18n/gl.po
odoo/addons/stock_picking_backorder_strategy/i18n/he.po
odoo/addons/stock_picking_backorder_strategy/i18n/hi.po
odoo/addons/stock_picking_backorder_strategy/i18n/hr.po
odoo/addons/stock_picking_backorder_strategy/i18n/hr_HR.po
odoo12_addon_stock_picking_backorder_strategy-12.0.1.0.1.99.dev15.dist-info/METADATA
odoo12_addon_stock_picking_backorder_strategy-12.0.1.0.1.99.dev15.dist-info/WHEEL
odoo12_addon_stock_picking_backorder_strategy-12.0.1.0.1.99.dev15.dist-info/top_level.txt
odoo12_addon_stock_picking_backorder_strategy-12.0.1.0.1.99.dev15.dist-info/RECORD
